pymergedocx/__init__.py
pymergedocx/cli.py
pymergedocx/pymergedocx.py
pymergedocx/engine/__init__.py
pymergedocx/engine/composer.json
pymergedocx/engine/composer.lock
pymergedocx/engine/composer.phar
pymergedocx/engine/merge_docx.php
pymergedocx/engine/vendor/.DS_Store
pymergedocx/engine/vendor/autoload.php
pymergedocx/engine/vendor/composer/ClassLoader.php
pymergedocx/engine/vendor/composer/LICENSE
pymergedocx/engine/vendor/composer/autoload_classmap.php
pymergedocx/engine/vendor/composer/autoload_namespaces.php
pymergedocx/engine/vendor/composer/autoload_psr4.php
pymergedocx/engine/vendor/composer/autoload_real.php
pymergedocx/engine/vendor/composer/autoload_static.php
pymergedocx/engine/vendor/composer/installed.json
pymergedocx/engine/vendor/krustnic/docx-merge/.gitignore
pymergedocx/engine/vendor/krustnic/docx-merge/README.md
pymergedocx/engine/vendor/krustnic/docx-merge/composer.json
pymergedocx/engine/vendor/krustnic/docx-merge/composer.lock
pymergedocx/engine/vendor/krustnic/docx-merge/phpunit.xml
pymergedocx/engine/vendor/krustnic/docx-merge/src/DocxMerge.php
pymergedocx/engine/vendor/krustnic/docx-merge/src/DocxMerge/Docx.php
pymergedocx/engine/vendor/krustnic/docx-merge/src/DocxMerge/Prettify.php
pymergedocx/engine/vendor/krustnic/docx-merge/src/libraries/TbsZip.php
pymergedocx/engine/vendor/krustnic/docx-merge/tests/DocxMergeTest.php
pymergedocx/engine/vendor/krustnic/docx-merge/tests/PrettifyTest.php
pymergedocx/engine/vendor/krustnic/docx-merge/tests/test_src/test_doc.docx
pymergedocx-0.1.4.dist-info/DESCRIPTION.rst
pymergedocx-0.1.4.dist-info/METADATA
pymergedocx-0.1.4.dist-info/RECORD
pymergedocx-0.1.4.dist-info/WHEEL
pymergedocx-0.1.4.dist-info/entry_points.txt
pymergedocx-0.1.4.dist-info/metadata.json
pymergedocx-0.1.4.dist-info/top_level.txt
