Metadata-Version: 2.0
Name: pymergedocx
Version: 0.1.4
Summary: python下调用php合并doc库
Home-page: https://github.com/x-debug/pymergedocx
Author: x-debug
Author-email: 512766594@qq.com
License: Apache Software License 2.0
Keywords: pymergedocx
Platform: UNKNOWN
Classifier: Development Status :: 2 - Pre-Alpha
Classifier: Intended Audience :: Developers
Classifier: License :: OSI Approved :: Apache Software License
Classifier: Natural Language :: English
Classifier: Programming Language :: Python :: 2
Classifier: Programming Language :: Python :: 2.7
Classifier: Programming Language :: Python :: 3
Classifier: Programming Language :: Python :: 3.4
Classifier: Programming Language :: Python :: 3.5
Classifier: Programming Language :: Python :: 3.6
Requires-Dist: Click (>=6.0)
